README.rst
setup.py
aiovalidator/__init__.py
aiovalidator.egg-info/PKG-INFO
aiovalidator.egg-info/SOURCES.txt
aiovalidator.egg-info/dependency_links.txt
aiovalidator.egg-info/requires.txt
aiovalidator.egg-info/top_level.txt
aiovalidator/fields/__init__.py
aiovalidator/fields/base.py
aiovalidator/fields/date.py
aiovalidator/fields/manager.py
aiovalidator/fields/number.py
aiovalidator/fields/string.py
aiovalidator/middlewares/__init__.py
aiovalidator/middlewares/exception.py
aiovalidator/middlewares/validator.py