Metadata-Version: 1.1
Name: aiovalidator
Version: 0.0.2
Summary: rest, restful validator aiohttp
Home-page: https://github.com/vir-mir
Author: Alexey Firsov
Author-email: virmir49@gmail.com
License: Apache-2.0
Download-URL: https://pypi.python.org/pypi/aiovalidator
Platform: POSIX
Classifier: License :: OSI Approved :: BSD License
Classifier: Intended Audience :: Developers
Classifier: Programming Language :: Python :: 3
Classifier: Programming Language :: Python :: 3.4
Classifier: Programming Language :: Python :: 3.5
Classifier: Operating System :: POSIX
Classifier: Operating System :: MacOS :: MacOS X
Classifier: Operating System :: Microsoft :: Windows
Classifier: Environment :: Web Environment
Classifier: Development Status :: 4 - Beta
Classifier: Topic :: Database
Classifier: Topic :: Database :: Front-Ends
